.DS_Store
innerverz/__init__.py
innerverz/data_process/__init__.py
innerverz/data_process/main.py
innerverz/deblurrer/__init__.py
innerverz/deblurrer/main.py
innerverz/deblurrer/nets.py
innerverz/deblurrer/test.py
innerverz/deca/__init__.py
innerverz/deca/main.py
innerverz/deca/test.py
innerverz/deca/models/FLAME.py
innerverz/deca/models/__init__.py
innerverz/deca/models/decoders.py
innerverz/deca/models/detectors.py
innerverz/deca/models/encoders.py
innerverz/deca/models/face_detectors.py
innerverz/deca/models/lbs.py
innerverz/deca/models/resnet.py
innerverz/deca/utils/__init__.py
innerverz/deca/utils/cfg.py
innerverz/deca/utils/lmks_756.py
innerverz/deca/utils/lmks_846.py
innerverz/deca/utils/renderer.py
innerverz/deca/utils/rotation_converter.py
innerverz/deca/utils/tensor_cropper.py
innerverz/deca/utils/tracker_utils.py
innerverz/deca/utils/util.py
innerverz/deca/utils/rasterizer/__init__.py
innerverz/deca/utils/rasterizer/setup.py
innerverz/deep3dmm/__init__.py
innerverz/deep3dmm/main.py
innerverz/deep3dmm/nets.py
innerverz/deep3dmm/test.py
innerverz/face_aligner/__init__.py
innerverz/face_aligner/graphic_utils.py
innerverz/face_aligner/landmark.py
innerverz/face_aligner/main.py
innerverz/face_aligner/retina_face.py
innerverz/face_aligner/test.py
innerverz/face_aligner/utils/__init__.py
innerverz/face_aligner/utils/face_align.py
innerverz/face_aligner/utils/transform.py
innerverz/face_alignment/__init__.py
innerverz/face_alignment/graphic_utils.py
innerverz/face_alignment/landmark.py
innerverz/face_alignment/main.py
innerverz/face_alignment/retina_face.py
innerverz/face_alignment/test.py
innerverz/face_alignment/utils/__init__.py
innerverz/face_alignment/utils/face_align.py
innerverz/face_alignment/utils/transform.py
innerverz/face_color_transfer/__init__.py
innerverz/face_color_transfer/main.py
innerverz/face_color_transfer/nets.py
innerverz/face_color_transfer/test.py
innerverz/face_color_transfer/sub_nets/__init__.py
innerverz-0.1.11.dist-info/LICENSE.txt
innerverz-0.1.11.dist-info/METADATA
innerverz-0.1.11.dist-info/WHEEL
innerverz-0.1.11.dist-info/top_level.txt
innerverz-0.1.11.dist-info/RECORD
